{
    "solutions": [
        {
            "id": 1,
            "title": "Two Sum",
            "route": "/1",
            "difficulty": "Easy",
            "description": "Given an array of integers nums and an integer target, return indices of the two numbers such that they add up to target.",
            "timeComplexity": "O(n)",
            "spaceComplexity": "O(n)"
        },
        {
            "id": 2,
            "title": "Add Two Numbers",
            "route": "/2",
            "difficulty": "Medium",
            "description": "You are given two non-empty linked lists representing two non-negative integers.",
            "timeComplexity": "O(max(m,n))",
            "spaceComplexity": "O(max(m,n))"
        },
        {
            "id": 11,
            "title": "Container With Most Water",
            "route": "/11",
            "difficulty": "Medium",
            "description": "You are given an integer array height of length n. There are n vertical lines drawn such that the two endpoints of the ith line are (i, 0) and (i, height[i]).",
            "timeComplexity": "O(n)",
            "spaceComplexity": "O(1)"
        },
        {
            "id": 36,
            "title": "Valid Sudoku",
            "route": "/36",
            "difficulty": "Medium",
            "description": "Determine if a 9 x 9 Sudoku board is valid.",
            "timeComplexity": "O(1)",
            "spaceComplexity": "O(1)"
        },
        {
            "id": 37,
            "title": "Sudoku Solver",
            "route": "/37",
            "difficulty": "Hard",
            "description": "Write a program to solve a Sudoku puzzle by filling the empty cells.",
            "timeComplexity": "O(9^(n*n))",
            "spaceComplexity": "O(n*n)"
        },
        {
            "id": 66,
            "title": "Plus One",
            "route": "/66",
            "difficulty": "Easy",
            "description": "Increment a large integer represented as an integer array by one and return the resulting array of digits.",
            "timeComplexity": "O(n)",
            "spaceComplexity": "O(1)"
        },
        {
            "id": 85,
            "title": "Maximal Rectangle",
            "route": "/85",
            "difficulty": "Hard",
            "description": "Find the largest rectangle containing only 1's in a binary matrix and return its area.",
            "timeComplexity": "O(r*c)",
            "spaceComplexity": "O(r*c)"
        },
        {
            "id": 120,
            "title": "Triangle",
            "route": "/120",
            "difficulty": "Medium",
            "description": "Given a triangle array, return the minimum path sum from top to bottom.",
            "timeComplexity": "O(n^2)",
            "spaceComplexity": "O(n)"
        },
        {
            "id": 165,
            "title": "Compare Version Numbers",
            "route": "/165",
            "difficulty": "Medium",
            "description": "Compare two version numbers version1 and version2.",
            "timeComplexity": "O(n+m)",
            "spaceComplexity": "O(n+m)"
        },
        {
            "id": 166,
            "title": "Fraction to Recurring Decimal",
            "route": "/166",
            "difficulty": "Medium",
            "description": "Given two integers representing the numerator and denominator of a fraction, return the fraction in string format.",
            "timeComplexity": "O(denominator)",
            "spaceComplexity": "O(denominator)"
        },
        {
            "id": 326,
            "title": "Power of Three",
            "route": "/326",
            "difficulty": "Easy",
            "description": "Given an integer n, return true if it is a power of three. Otherwise, return false.",
            "timeComplexity": "O(log n)",
            "spaceComplexity": "O(1)"
        },
        {
            "id": 342,
            "title": "Power of Four",
            "route": "/342",
            "difficulty": "Easy",
            "description": "Given an integer n, return true if it is a power of four. Otherwise, return false.",
            "timeComplexity": "O(1)",
            "spaceComplexity": "O(1)"
        },
        {
            "id": 407,
            "title": "Trapping Rain Water II",
            "route": "/407",
            "difficulty": "Hard",
            "description": "Given an m x n integer matrix heightMap representing the height of each unit cell in a 2D elevation map, return the volume of water it can trap after raining.",
            "timeComplexity": "O(m*n*log(m*n))",
            "spaceComplexity": "O(m*n)"
        },
        {
            "id": 417,
            "title": "Pacific Atlantic Water Flow",
            "route": "/417",
            "difficulty": "Medium",
            "description": "There is an m x n rectangular island that borders both the Pacific Ocean and Atlantic Ocean.",
            "timeComplexity": "O(m*n)",
            "spaceComplexity": "O(m*n)"
        },
        {
            "id": 474,
            "title": "Ones and Zeroes",
            "route": "/474",
            "difficulty": "Medium",
            "description": "You are given an array of binary strings strs and two integers m and n. Return the size of the largest subset of strs such that there are at most m 0's and n 1's in the subset.",
            "timeComplexity": "O(len(strs) * m * n)",
            "spaceComplexity": "O(m * n)"
        },
        {
            "id": 498,
            "title": "Diagonal Traverse",
            "route": "/498",
            "difficulty": "Medium",
            "description": "Given an m x n matrix mat, return an array of all the elements of the array in a diagonal order.",
            "timeComplexity": "O(m*n)",
            "spaceComplexity": "O(1)"
        },
        {
            "id": 611,
            "title": "Valid Triangle Number",
            "route": "/611",
            "difficulty": "Medium",
            "description": "Given an integer array nums, return the number of triplets chosen from the array that can make triangles if we take them as side lengths of a triangle.",
            "timeComplexity": "O(n^2)",
            "spaceComplexity": "O(1)"
        },
        {
            "id": 679,
            "title": "24 Game",
            "route": "/679",
            "difficulty": "Hard",
            "description": "You are given an integer array cards of length 4. You have four cards, each containing a number in the range [1, 9].",
            "timeComplexity": "O(1)",
            "spaceComplexity": "O(1)"
        },
        {
            "id": 712,
            "title": "Minimum ASCII Delete Sum for Two Strings",
            "route": "/712",
            "difficulty": "Medium",
            "description": "Given two strings s1 and s2, return the lowest ASCII sum of deleted characters to make two strings equal.",
            "timeComplexity": "O(n*m)",
            "spaceComplexity": "O(n*m)"
        },
        {
            "id": 717,
            "title": "1-bit and 2-bit Characters",
            "route": "/717",
            "difficulty": "Easy",
            "description": "We have two special characters: The first character can be represented by one bit 0. The second character can be represented by two bits (10 or 11). Given a binary array bits that ends with 0, return true if the last character must be a one-bit character.",
            "timeComplexity": "O(n)",
            "spaceComplexity": "O(1)"
        },
        {
            "id": 756,
            "title": "Pyramid Transition Matrix",
            "route": "/756",
            "difficulty": "Medium",
            "description": "Determine if you can build a pyramid all the way to the top using specific triangular patterns allowed.",
            "timeComplexity": "O(allowed^base)",
            "spaceComplexity": "O(base^2)"
        },
        {
            "id": 757,
            "title": "Set Intersection Size At Least Two",
            "route": "/757",
            "difficulty": "Hard",
            "description": "You are given a 2D integer array intervals where intervals[i] = [start_i, end_i] represents all the integers from start_i to end_i inclusively. A containing set is an array nums where each interval from intervals has at least two integers in nums. Return the minimum possible size of a containing set.",
            "timeComplexity": "O(n log n)",
            "spaceComplexity": "O(1)"
        },
        {
            "id": 778,
            "title": "Swim in Rising Water",
            "route": "/778",
            "difficulty": "Hard",
            "description": "You are given an n x n integer matrix grid where each value grid[i][j] represents the elevation at that point (i, j).",
            "timeComplexity": "O(n^2*log(n^2))",
            "spaceComplexity": "O(n^2)"
        },
        {
            "id": 812,
            "title": "Largest Triangle Area",
            "route": "/812",
            "difficulty": "Easy",
            "description": "Given an array of points on the X-Y plane points where points[i] = [xi, yi], return the area of the largest triangle that can be formed by any three different points.",
            "timeComplexity": "O(n^3)",
            "spaceComplexity": "O(1)"
        },
        {
            "id": 837,
            "title": "New 21 Game",
            "route": "/837",
            "difficulty": "Medium",
            "description": "Alice plays the following game, loosely based on the card game \"21\".",
            "timeComplexity": "O(k + w)",
            "spaceComplexity": "O(k + w)"
        },
        {
            "id": 840,
            "title": "Magic Squares In Grid",
            "route": "/840",
            "difficulty": "Medium",
            "description": "Given a row x col grid of integers, how many 3 x 3 contiguous magic square subgrids are there?",
            "timeComplexity": "O(r*c)",
            "spaceComplexity": "O(1)"
        },
        {
            "id": 865,
            "title": "Smallest Subtree with all the Deepest Nodes",
            "route": "/865",
            "difficulty": "Medium",
            "description": "Given the root of a binary tree, return the smallest subtree such that it contains all the deepest nodes.",
            "timeComplexity": "O(n)",
            "spaceComplexity": "O(h)"
        },
        {
            "id": 869,
            "title": "Reordered Power of 2",
            "route": "/869",
            "difficulty": "Medium",
            "description": "You are given an integer n. We reorder the digits in any order (including the original order) such that the leading digit is not zero.",
            "timeComplexity": "O(log n)",
            "spaceComplexity": "O(log n)"
        },
        {
            "id": 944,
            "title": "Delete Columns to Make Sorted",
            "route": "/944",
            "difficulty": "Easy",
            "description": "You are given an array of n strings strs, all of the same length. Return the number of columns that you will delete.",
            "timeComplexity": "O(n*m)",
            "spaceComplexity": "O(1)"
        },
        {
            "id": 955,
            "title": "Delete Columns to Make Sorted II",
            "route": "/955",
            "difficulty": "Medium",
            "description": "Return the minimum possible number of deletion indices such that the final strings are in lexicographic order.",
            "timeComplexity": "O(n*m)",
            "spaceComplexity": "O(n)"
        },
        {
            "id": 960,
            "title": "Delete Columns to Make Sorted III",
            "route": "/960",
            "difficulty": "Hard",
            "description": "Return the minimum possible number of columns to delete such that the remaining columns form a non-decreasing sequence.",
            "timeComplexity": "O(n^2)",
            "spaceComplexity": "O(n^2)"
        },
        {
            "id": 961,
            "title": "N-Repeated Element in Size 2N Array",
            "route": "/961",
            "difficulty": "Easy",
            "description": "Exactly one element of nums is repeated n times in an array of size 2n. Return that element.",
            "timeComplexity": "O(n)",
            "spaceComplexity": "O(1)"
        },
        {
            "id": 966,
            "title": "Vowel Spellchecker",
            "route": "/966",
            "difficulty": "Medium",
            "description": "Given a wordlist, we want to implement a spellchecker that converts a query word into a correct word.",
            "timeComplexity": "O(n + m)",
            "spaceComplexity": "O(n + m)"
        },
        {
            "id": 976,
            "title": "Largest Perimeter Triangle",
            "route": "/976",
            "difficulty": "Easy",
            "description": "Given an integer array nums, return the largest perimeter of a triangle with a non-zero area, formed from three of these lengths.",
            "timeComplexity": "O(n log n)",
            "spaceComplexity": "O(1)"
        },
        {
            "id": 1015,
            "title": "Smallest Integer Divisible by K",
            "route": "/1015",
            "difficulty": "Medium",
            "description": "Given a positive integer k, you need to find the length of the smallest positive integer n such that n is divisible by k.",
            "timeComplexity": "O(k)",
            "spaceComplexity": "O(1)"
        },
        {
            "id": 1018,
            "title": "Binary Prefix Divisible By 5",
            "route": "/1018",
            "difficulty": "Easy",
            "description": "Return an array of booleans answer where answer[i] is true if the i-th binary prefix is divisible by 5.",
            "timeComplexity": "O(n)",
            "spaceComplexity": "O(1)"
        },
        {
            "id": 1039,
            "title": "Minimum Score Triangulation of Polygon",
            "route": "/1039",
            "difficulty": "Medium",
            "description": "You have a convex n-sided polygon where each vertex has an integer value.",
            "timeComplexity": "O(n^3)",
            "spaceComplexity": "O(n^2)"
        },
        {
            "id": 1161,
            "title": "Maximum Level Sum of a Binary Tree",
            "route": "/1161",
            "difficulty": "Medium",
            "description": "Return the smallest level x such that the sum of all node values at level x is maximal.",
            "timeComplexity": "O(n)",
            "spaceComplexity": "O(n)"
        },
        {
            "id": 1200,
            "title": "Minimum Absolute Difference",
            "route": "/1200",
            "difficulty": "Medium",
            "description": "Given an array of distinct integers arr, find all pairs of elements with the minimum absolute difference of any two elements. Return a list of pairs in ascending order (with respect to pairs), each...",
            "timeComplexity": "O(n)",
            "spaceComplexity": "O(1)"
        },
        {
            "id": 1262,
            "title": "Greatest Sum Divisible by Three",
            "route": "/1262",
            "difficulty": "Medium",
            "description": "Given an integer array nums, return the maximum possible sum of elements of the array such that it is divisible by three.",
            "timeComplexity": "O(n)",
            "spaceComplexity": "O(1)"
        },
        {
            "id": 1266,
            "title": "Minimum Time Visiting All Points",
            "route": "/1266",
            "difficulty": "Easy",
            "description": "Return the minimum time in seconds to visit all the points in the order given by points.",
            "timeComplexity": "O(n)",
            "spaceComplexity": "O(1)"
        },
        {
            "id": 1277,
            "title": "Count Square Submatrices with All Ones",
            "route": "/1277",
            "difficulty": "Medium",
            "description": "Given a m * n matrix of ones and zeros, return how many square submatrices have all ones.",
            "timeComplexity": "O(m*n)",
            "spaceComplexity": "O(1)"
        },
        {
            "id": 1292,
            "title": "Maximum Side Length of a Square with Sum Less than or Equal to Threshold",
            "route": "/1292",
            "difficulty": "Medium",
            "description": "Return the maximum side-length of a square with a sum less than or equal to threshold.",
            "timeComplexity": "O(m*n*log(min(m,n)))",
            "spaceComplexity": "O(m*n)"
        },
        {
            "id": 1304,
            "title": "Find N Unique Integers Sum up to Zero",
            "route": "/1304",
            "difficulty": "Easy",
            "description": "Given an integer n, return any array containing n unique integers such that they add up to 0.",
            "timeComplexity": "O(n)",
            "spaceComplexity": "O(1)"
        },
        {
            "id": 1317,
            "title": "Convert Integer to the Sum of Two No-Zero Integers",
            "route": "/1317",
            "difficulty": "Easy",
            "description": "Given an integer n. No-Zero integer is a positive integer which doesn't contain any 0 in its decimal representation.",
            "timeComplexity": "O(n)",
            "spaceComplexity": "O(1)"
        },
        {
            "id": 1323,
            "title": "Maximum 69 Number",
            "route": "/1323",
            "difficulty": "Easy",
            "description": "You are given a positive integer num consisting only of digits 6 and 9.",
            "timeComplexity": "O(log n)",
            "spaceComplexity": "O(1)"
        },
        {
            "id": 1339,
            "title": "Maximum Product of Splitted Binary Tree",
            "route": "/1339",
            "difficulty": "Medium",
            "description": "Split the binary tree into two subtrees by removing one edge such that the product of the sums of the subtrees is maximized.",
            "timeComplexity": "O(n)",
            "spaceComplexity": "O(h)"
        },
        {
            "id": 1351,
            "title": "Count Negative Numbers in a Sorted Matrix",
            "route": "/1351",
            "difficulty": "Easy",
            "description": "Given a sorted m x n matrix, return the number of negative numbers in the grid.",
            "timeComplexity": "O(m + n)",
            "spaceComplexity": "O(1)"
        },
        {
            "id": 1390,
            "title": "Four Divisors",
            "route": "/1390",
            "difficulty": "Medium",
            "description": "Given an integer array nums, return the sum of divisors of the integers in that array that have exactly four divisors.",
            "timeComplexity": "O(n * sqrt(val))",
            "spaceComplexity": "O(1)"
        },
        {
            "id": 1411,
            "title": "Number of Ways to Paint N × 3 Grid",
            "route": "/1411",
            "difficulty": "Hard",
            "description": "Return the number of ways you can paint a n x 3 grid with three colors such that no two adjacent cells have the same color.",
            "timeComplexity": "O(n)",
            "spaceComplexity": "O(1)"
        },
        {
            "id": 1437,
            "title": "Check If All 1's Are at Least Length K Places Away",
            "route": "/1437",
            "difficulty": "Easy",
            "description": "Given an binary array nums and an integer k, return true if all 1's are at least k places away from each other, otherwise return false.",
            "timeComplexity": "O(n)",
            "spaceComplexity": "O(1)"
        },
        {
            "id": 1458,
            "title": "Max Dot Product of Two Subsequences",
            "route": "/1458",
            "difficulty": "Hard",
            "description": "Return the maximum dot product between non-empty subsequences of nums1 and nums2 with the same length.",
            "timeComplexity": "O(n*m)",
            "spaceComplexity": "O(m)"
        },
        {
            "id": 1488,
            "title": "Avoid Flood in The City",
            "route": "/1488",
            "difficulty": "Medium",
            "description": "Your country has an infinite number of lakes. Initially, all the lakes are empty, but when it rains for the nth day, the nth lake becomes full of water.",
            "timeComplexity": "O(n log n)",
            "spaceComplexity": "O(n)"
        },
        {
            "id": 1493,
            "title": "Longest Subarray of 1's After Deleting One Element",
            "route": "/1493",
            "difficulty": "Medium",
            "description": "Given a binary array nums, you should delete one element from it.",
            "timeComplexity": "O(n)",
            "spaceComplexity": "O(1)"
        },
        {
            "id": 1504,
            "title": "Count Submatrices With All Ones",
            "route": "/1504",
            "difficulty": "Medium",
            "description": "Given a rows * columns matrix mat of ones and zeros, return how many submatrices have all ones.",
            "timeComplexity": "O(m*n)",
            "spaceComplexity": "O(1)"
        },
        {
            "id": 1513,
            "title": "Number of Substrings With Only 1s",
            "route": "/1513",
            "difficulty": "Medium",
            "description": "Given a binary string s, return the number of substrings with all characters equal to 1. Since the answer may be too large, return it modulo 10^9 + 7.",
            "timeComplexity": "O(n)",
            "spaceComplexity": "O(1)"
        },
        {
            "id": 1518,
            "title": "Water Bottles",
            "route": "/1518",
            "difficulty": "Easy",
            "description": "Given numBottles full water bottles, you can exchange numExchange empty water bottles for one full water bottle.",
            "timeComplexity": "O(log n)",
            "spaceComplexity": "O(1)"
        },
        {
            "id": 1523,
            "title": "Count Odd Numbers in an Interval Range",
            "route": "/1523",
            "difficulty": "Easy",
            "description": "Given two non-negative integers low and high, return the count of odd numbers between low and high (inclusive).",
            "timeComplexity": "O(1)",
            "spaceComplexity": "O(1)"
        },
        {
            "id": 1526,
            "title": "Minimum Number of Increments on Subarrays to Form a Target Array",
            "route": "/1526",
            "difficulty": "Medium",
            "description": "You are given an integer array target. You have an integer array initial of the same size as target with all elements initially zeros. In one operation you can choose any subarray from initial and increment each value by one. Return the minimum number of operations to form a target array from initial.",
            "timeComplexity": "O(n)",
            "spaceComplexity": "O(1)"
        },
        {
            "id": 1578,
            "title": "Minimum Time to Make Rope Colorful",
            "route": "/1578",
            "difficulty": "Medium",
            "description": "Alice has n balloons arranged on a rope. You are given a 0-indexed string colors where colors[i] is the color of the ith balloon. Alice wants the rope to be colorful, meaning that no two consecutive balloons are of the same color. You are given a 0-indexed integer array neededTime where neededTime[i] is the time (in seconds) that Alice needs to remove the ith balloon from the rope. Return the minimum time Alice needs to make the rope colorful.",
            "timeComplexity": "O(n)",
            "spaceComplexity": "O(1)"
        },
        {
            "id": 1590,
            "title": "Make Sum Divisible by P",
            "route": "/1590",
            "difficulty": "Medium",
            "description": "Given an array of positive integers nums, remove the smallest subarray such that the sum of the remaining elements is divisible by p.",
            "timeComplexity": "O(n)",
            "spaceComplexity": "O(n)"
        },
        {
            "id": 1611,
            "title": "Minimum One Bit Operations to Make Integers Zero",
            "route": "/1611",
            "difficulty": "Hard",
            "description": "Given an integer n, you must transform it into 0 using the minimum number of operations. In each operation, you can change the rightmost (0th) bit in the binary representation of n, or change the ith bit in the binary representation of n if the (i-1)th bit is set to 1 and the (i-2)th through 0th bits are set to 0. Return the minimum number of operations to make n equal to 0.",
            "timeComplexity": "O(log n)",
            "spaceComplexity": "O(1)"
        },
        {
            "id": 1625,
            "title": "Lexicographically Smallest String After Applying Operations",
            "route": "/1625",
            "difficulty": "Medium",
            "description": "You are given a string s of even length consisting of digits from 0 to 9, and two integers a and b.",
            "timeComplexity": "O(n^2)",
            "spaceComplexity": "O(n)"
        },
        {
            "id": 1716,
            "title": "Calculate Money in Leetcode Bank",
            "route": "/1716",
            "difficulty": "Easy",
            "description": "Hercy wants to save money for his first car. He puts money in the Leetcode bank every day.",
            "timeComplexity": "O(1)",
            "spaceComplexity": "O(1)"
        },
        {
            "id": 1733,
            "title": "Minimum Number of People to Teach",
            "route": "/1733",
            "difficulty": "Medium",
            "description": "On a social network consisting of m users and some friendships between users, two users can communicate with each other if they know a common language.",
            "timeComplexity": "O(m*n*l)",
            "spaceComplexity": "O(m*n*l)"
        },
        {
            "id": 1792,
            "title": "Maximum Average Pass Ratio",
            "route": "/1792",
            "difficulty": "Medium",
            "description": "There is a school that has classes of students and each class will be having a final exam.",
            "timeComplexity": "O(n log n)",
            "spaceComplexity": "O(n)"
        },
        {
            "id": 1877,
            "title": "Minimize Maximum Pair Sum in Array",
            "route": "/1877",
            "difficulty": "Medium",
            "description": "The pair sum of a pair (a,b) is equal to a + b. The maximum pair sum is the largest pair sum in a list of pairs. Given an array nums of even length n, pair up the elements of nums into n / 2 pairs ...",
            "timeComplexity": "O(n)",
            "spaceComplexity": "O(1)"
        },
        {
            "id": 1895,
            "title": "Largest Magic Square",
            "route": "/1895",
            "difficulty": "Medium",
            "description": "Return the side length k of the largest magic square that can be found within an m x n integer grid.",
            "timeComplexity": "O(m*n*min(m,n)^2)",
            "spaceComplexity": "O(1)"
        },
        {
            "id": 1912,
            "title": "Design Movie Rental System",
            "route": "/1912",
            "difficulty": "Hard",
            "description": "You have a movie renting company consisting of n movie shops.",
            "timeComplexity": "O(log n)",
            "spaceComplexity": "O(n)"
        },
        {
            "id": 1925,
            "title": "Count Square Sum Triples",
            "route": "/1925",
            "difficulty": "Easy",
            "description": "A square triple (a, b, c) is a triple where a, b, and c are integers and a^2 + b^2 = c^2. Return the number of square triples such that 1 <= a, b, c <= n.",
            "timeComplexity": "O(n^2)",
            "spaceComplexity": "O(1)"
        },
        {
            "id": 1930,
            "title": "Unique Length-3 Palindromic Subsequences",
            "route": "/1930",
            "difficulty": "Medium",
            "description": "Given a string s, return the number of unique palindromes of length three that are a subsequence of s.",
            "timeComplexity": "O(n)",
            "spaceComplexity": "O(1)"
        },
        {
            "id": 1935,
            "title": "Maximum Number of Words You Can Type",
            "route": "/1935",
            "difficulty": "Easy",
            "description": "There is a malfunctioning keyboard where some letter keys do not work.",
            "timeComplexity": "O(n*m)",
            "spaceComplexity": "O(1)"
        },
        {
            "id": 1970,
            "title": "Last Day Where You Can Still Cross",
            "route": "/1970",
            "difficulty": "Hard",
            "description": "Find the last day where it is possible to walk from the top to the bottom of a matrix that is gradually flooding.",
            "timeComplexity": "O(row*col*log(row*col))",
            "spaceComplexity": "O(row*col)"
        },
        {
            "id": 1975,
            "title": "Maximum Matrix Sum",
            "route": "/1975",
            "difficulty": "Medium",
            "description": "Maximize the summation of a matrix's elements by flipping adjacent pairs' signs.",
            "timeComplexity": "O(n^2)",
            "spaceComplexity": "O(1)"
        },
        {
            "id": 1984,
            "title": "Minimum Difference Between Highest and Lowest of K Scores",
            "route": "/1984",
            "difficulty": "Medium",
            "description": "You are given a 0-indexed integer array nums, where nums[i] represents the score of the ith student. You are also given an integer k. Pick the scores of any k students from the array so that the di...",
            "timeComplexity": "O(n)",
            "spaceComplexity": "O(1)"
        },
        {
            "id": 2011,
            "title": "Final Value of Variable After Performing Operations",
            "route": "/2011",
            "difficulty": "Easy",
            "description": "There is a programming language with only four operations and one variable X.",
            "timeComplexity": "O(n)",
            "spaceComplexity": "O(1)"
        },
        {
            "id": 2043,
            "title": "Simple Bank System",
            "route": "/2043",
            "difficulty": "Medium",
            "description": "You have been tasked with writing a program for a popular bank that will automate all its incoming transactions (transfer, deposit, and withdraw). The bank has n accounts numbered from 1 to n. The initial balance of each account is stored in a 0-indexed integer array balance, with the (i + 1)th account having an initial balance of balance[i]. Execute all the valid transactions.",
            "timeComplexity": "O(1)",
            "spaceComplexity": "O(n)"
        },
        {
            "id": 2048,
            "title": "Next Greater Numerically Balanced Number",
            "route": "/2048",
            "difficulty": "Medium",
            "description": "An integer x is numerically balanced if for every digit d in x, the frequency of d in x is equal to d.",
            "timeComplexity": "O(n log n)",
            "spaceComplexity": "O(1)"
        },
        {
            "id": 2054,
            "title": "Two Best Non-Overlapping Events",
            "route": "/2054",
            "difficulty": "Medium",
            "description": "You can attend at most two non-overlapping events. Return the maximum sum of values.",
            "timeComplexity": "O(n log n)",
            "spaceComplexity": "O(n)"
        },
        {
            "id": 2092,
            "title": "Find All People With Secret",
            "route": "/2092",
            "difficulty": "Hard",
            "description": "You are given an integer n indicating there are n people. You are also given a meetings array. Return a list of all the people that have the secret after all the meetings have taken place.",
            "timeComplexity": "O(m log m)",
            "spaceComplexity": "O(n + m)"
        },
        {
            "id": 2110,
            "title": "Number of Smooth Descent Periods of a Stock",
            "route": "/2110",
            "difficulty": "Medium",
            "description": "You are given an integer array prices representing the daily price history of a stock. Return the number of smooth descent periods.",
            "timeComplexity": "O(n)",
            "spaceComplexity": "O(1)"
        },
        {
            "id": 2125,
            "title": "Number of Laser Beams in a Bank",
            "route": "/2125",
            "difficulty": "Medium",
            "description": "Anti-theft security devices are activated inside a bank. You are given a 0-indexed binary string array bank representing the floor plan of the bank, which is an m x n 2D matrix. bank[i] represents the ith row, consisting of '0's and '1's. '0' means the cell is empty, while '1' means the cell has a security device. There is one laser beam between any two security devices if both devices are in different rows and there are no security devices in the rows between them. Return the total number of laser beams in the bank.",
            "timeComplexity": "O(m*n)",
            "spaceComplexity": "O(1)"
        },
        {
            "id": 2141,
            "title": "Maximum Running Time of N Computers",
            "route": "/2141",
            "difficulty": "Medium",
            "description": "You have n computers and a battery array. Return the maximum number of minutes you can run all n computers simultaneously.",
            "timeComplexity": "O(m log S)",
            "spaceComplexity": "O(1)"
        },
        {
            "id": 2147,
            "title": "Number of Ways to Divide a Long Corridor",
            "route": "/2147",
            "difficulty": "Hard",
            "description": "Return the number of ways you can divide the corridor such that each section contains exactly two seats.",
            "timeComplexity": "O(n)",
            "spaceComplexity": "O(1)"
        },
        {
            "id": 2154,
            "title": "Keep Multiplying Found Values by Two",
            "route": "/2154",
            "difficulty": "Easy",
            "description": "You are given an array of integers nums. You are also given an integer original which is the first number that needs to be searched for in nums. You then do the following steps: If original is found in nums, multiply it by two (i.e., set original = 2 * original). Otherwise, stop the process. Repeat this process with the new number as long as you keep finding the number. Return the final value of original.",
            "timeComplexity": "O(n)",
            "spaceComplexity": "O(n)"
        },
        {
            "id": 2169,
            "title": "Count Operations to Obtain Zero",
            "route": "/2169",
            "difficulty": "Easy",
            "description": "You are given two non-negative integers num1 and num2. In one operation, if num1 >= num2, you must subtract num2 from num1, otherwise subtract num1 from num2. Return the number of operations required to make either num1 = 0 or num2 = 0.",
            "timeComplexity": "O(log(min(num1, num2)))",
            "spaceComplexity": "O(1)"
        },
        {
            "id": 2197,
            "title": "Replace Non-Coprime Numbers in Array",
            "route": "/2197",
            "difficulty": "Hard",
            "description": "You are given a list of integers nums. Consider the following operation: choose any two adjacent elements and replace them with their LCM.",
            "timeComplexity": "O(n log n)",
            "spaceComplexity": "O(n)"
        },
        {
            "id": 2211,
            "title": "Count Collisions on a Road",
            "route": "/2211",
            "difficulty": "Medium",
            "description": "You are given a string directions. Return the number of collisions.",
            "timeComplexity": "O(n)",
            "spaceComplexity": "O(1)"
        },
        {
            "id": 2221,
            "title": "Find Triangular Sum of an Array",
            "route": "/2221",
            "difficulty": "Medium",
            "description": "You are given a 0-indexed integer array nums, where nums[i] is a digit between 0 and 9 (inclusive).",
            "timeComplexity": "O(n^2)",
            "spaceComplexity": "O(1)"
        },
        {
            "id": 2257,
            "title": "Count Unguarded Cells in the Grid",
            "route": "/2257",
            "difficulty": "Medium",
            "description": "You are given two integers m and n representing a 0-indexed m x n grid. You are also given two 2D integer arrays guards and walls where guards[i] = [row_i, col_i] and walls[j] = [row_j, col_j] represent the positions of the ith guard and jth wall respectively. A guard can see every cell in the four cardinal directions (north, east, south, or west) starting from their position unless obstructed by a wall or another guard. A cell is guarded if there is at least one guard that can see it. Return the number of unoccupied cells that are not guarded.",
            "timeComplexity": "O(m*n)",
            "spaceComplexity": "O(m*n)"
        },
        {
            "id": 2264,
            "title": "Largest 3-Same-Digit Number in String",
            "route": "/2264",
            "difficulty": "Easy",
            "description": "You are given a string num representing a large integer. An integer is good if it meets the following conditions.",
            "timeComplexity": "O(n)",
            "spaceComplexity": "O(1)"
        },
        {
            "id": 2273,
            "title": "Find Resultant Array After Removing Anagrams",
            "route": "/2273",
            "difficulty": "Easy",
            "description": "You are given a 0-indexed string array words, where words[i] consists of lowercase English letters.",
            "timeComplexity": "O(n*m log m)",
            "spaceComplexity": "O(n*m)"
        },
        {
            "id": 2300,
            "title": "Successful Pairs of Spells and Potions",
            "route": "/2300",
            "difficulty": "Medium",
            "description": "You are given two positive integer arrays spells and potions, of length n and m respectively.",
            "timeComplexity": "O(m log m + n log m)",
            "spaceComplexity": "O(1)"
        },
        {
            "id": 2327,
            "title": "Number of People Aware of a Secret",
            "route": "/2327",
            "difficulty": "Medium",
            "description": "On day 1, one person discovers a secret.",
            "timeComplexity": "O(n)",
            "spaceComplexity": "O(n)"
        },
        {
            "id": 2348,
            "title": "Number of Zero-Filled Subarrays",
            "route": "/2348",
            "difficulty": "Medium",
            "description": "Given an integer array nums, return the number of subarrays filled with 0.",
            "timeComplexity": "O(n)",
            "spaceComplexity": "O(1)"
        },
        {
            "id": 2353,
            "title": "Design a Food Rating System",
            "route": "/2353",
            "difficulty": "Medium",
            "description": "Design a food rating system that can do the following.",
            "timeComplexity": "O(log n)",
            "spaceComplexity": "O(n)"
        },
        {
            "id": 2402,
            "title": "Meeting Rooms III",
            "route": "/2402",
            "difficulty": "Hard",
            "description": "Return the number of the room that held the most meetings in a system where meetings can be delayed.",
            "timeComplexity": "O(m log m + m log n)",
            "spaceComplexity": "O(n)"
        },
        {
            "id": 2435,
            "title": "Paths in Matrix Whose Sum Is Divisible by K",
            "route": "/2435",
            "difficulty": "Hard",
            "description": "Return the number of good paths in the matrix where the sum of elements is divisible by k.",
            "timeComplexity": "O(m*n*k)",
            "spaceComplexity": "O(m*n*k)"
        },
        {
            "id": 2438,
            "title": "Range Product Queries of Powers",
            "route": "/2438",
            "difficulty": "Medium",
            "description": "Given a positive integer n, there exists a 0-indexed array called powers, composed of the minimum number of powers of 2 that sum to n.",
            "timeComplexity": "O(q * log n)",
            "spaceComplexity": "O(log n)"
        },
        {
            "id": 2483,
            "title": "Minimum Penalty for a Shop",
            "route": "/2483",
            "difficulty": "Medium",
            "description": "Return the earliest hour at which the shop must be closed to incur a minimum penalty based on customer visit logs.",
            "timeComplexity": "O(n)",
            "spaceComplexity": "O(1)"
        },
        {
            "id": 2528,
            "title": "Maximize the Minimum Powered City",
            "route": "/2528",
            "difficulty": "Hard",
            "description": "You are given a 0-indexed integer array stations of length n, where stations[i] represents the number of power stations in the ith city. Each power station can supply power to every city in a range [i - r, i + r] (inclusive). You are also given an integer r that represents the range of each power station, and an integer k representing the number of additional power stations you can place. Return the maximum possible minimum power supply of all cities after placing at most k additional power stations optimally.",
            "timeComplexity": "O(n log(sum(stations) + k))",
            "spaceComplexity": "O(n)"
        },
        {
            "id": 2536,
            "title": "Increment Submatrices by One",
            "route": "/2536",
            "difficulty": "Medium",
            "description": "You are given a positive integer n, indicating that we initially have an n x n 0-indexed integer matrix mat filled with zeroes. You are also given a 2D integer array query. For each query[i] = [row1_i, col1_i, row2_i, col2_i], you should do the following operation: Add 1 to every element in the submatrix with the top left corner (row1_i, col1_i) and the bottom right corner (row2_i, col2_i). Return the matrix mat after performing every query.",
            "timeComplexity": "O(q * n + n^2)",
            "spaceComplexity": "O(n^2)"
        },
        {
            "id": 2598,
            "title": "Smallest Missing Non-negative Integer After Operations",
            "route": "/2598",
            "difficulty": "Medium",
            "description": "You are given a 0-indexed integer array nums and an integer value.",
            "timeComplexity": "O(n)",
            "spaceComplexity": "O(n)"
        },
        {
            "id": 2654,
            "title": "Minimum Number of Operations to Make All Array Elements Equal to 1",
            "route": "/2654",
            "difficulty": "Medium",
            "description": "You are given a 0-indexed array nums consisting of positive integers. You can perform the following operation on the array any number of times: Select an index i such that 0 <= i < n - 1 and replace either nums[i] or nums[i+1] with their GCD. Return the minimum number of operations required to make all elements of nums equal to 1. If it is impossible, return -1.",
            "timeComplexity": "O(n^2)",
            "spaceComplexity": "O(1)"
        },
        {
            "id": 2749,
            "title": "Minimum Operations to Make the Integer Zero",
            "route": "/2749",
            "difficulty": "Medium",
            "description": "You are given two integers num1 and num2.",
            "timeComplexity": "O(1)",
            "spaceComplexity": "O(1)"
        },
        {
            "id": 2785,
            "title": "Sort Vowels in a String",
            "route": "/2785",
            "difficulty": "Medium",
            "description": "Given a 0-indexed string s, permute the string s such that the vowels are in sorted order.",
            "timeComplexity": "O(n log n)",
            "spaceComplexity": "O(n)"
        },
        {
            "id": 2787,
            "title": "Ways to Express an Integer as Sum of Powers",
            "route": "/2787",
            "difficulty": "Medium",
            "description": "Given two positive integers n and x.",
            "timeComplexity": "O(n^(1/x))",
            "spaceComplexity": "O(n^(1/x))"
        },
        {
            "id": 2872,
            "title": "Maximum Number of K-Divisible Components",
            "route": "/2872",
            "difficulty": "Hard",
            "description": "A valid split of the tree is obtained by removing any set of edges from the tree such that the resulting components all have values that are divisible by k. Return the maximum number of components in any valid split.",
            "timeComplexity": "O(n)",
            "spaceComplexity": "O(n)"
        },
        {
            "id": 2943,
            "title": "Maximize Area of Square Hole in Grid",
            "route": "/2943",
            "difficulty": "Medium",
            "description": "Maximize the area of a square hole that can be created by removing horizontal and vertical bars from a grid.",
            "timeComplexity": "O(m log m + n log n)",
            "spaceComplexity": "O(1)"
        },
        {
            "id": 2975,
            "title": "Maximum Square Area by Removing Fences From a Field",
            "route": "/2975",
            "difficulty": "Hard",
            "description": "Return the maximum area of a square that can be formed by removing horizontal and vertical fences.",
            "timeComplexity": "O(n^2)",
            "spaceComplexity": "O(n^2)"
        },
        {
            "id": 2976,
            "title": "Minimum Cost to Convert String I",
            "route": "/2976",
            "difficulty": "Medium",
            "description": "You are given two strings source and target, both of length n and consisting of lowercase English letters. You are also given two character arrays original and changed, and an integer array cost, w...",
            "timeComplexity": "O(n)",
            "spaceComplexity": "O(1)"
        },
        {
            "id": 2977,
            "title": "Minimum Cost to Convert String II",
            "route": "/2977",
            "difficulty": "Medium",
            "description": "You are given two strings source and target, both consisting of lowercase English letters. You are also given two string arrays original and changed, and an integer array cost, where cost[i] repres...",
            "timeComplexity": "O(n)",
            "spaceComplexity": "O(1)"
        },
        {
            "id": 3000,
            "title": "Maximum Area of Longest Diagonal Rectangle",
            "route": "/3000",
            "difficulty": "Easy",
            "description": "You are given a 2D 0-indexed integer array dimensions.",
            "timeComplexity": "O(n)",
            "spaceComplexity": "O(1)"
        },
        {
            "id": 3003,
            "title": "Maximize the Number of Partitions After Operations",
            "route": "/3003",
            "difficulty": "Hard",
            "description": "You are given a 0-indexed string s of length n consisting of only lowercase English letters.",
            "timeComplexity": "O(n^2)",
            "spaceComplexity": "O(n^2)"
        },
        {
            "id": 3005,
            "title": "Count Elements With Maximum Frequency",
            "route": "/3005",
            "difficulty": "Easy",
            "description": "You are given an array nums consisting of positive integers.",
            "timeComplexity": "O(n)",
            "spaceComplexity": "O(n)"
        },
        {
            "id": 3021,
            "title": "Alice and Bob Playing Flower Game",
            "route": "/3021",
            "difficulty": "Medium",
            "description": "Alice and Bob are playing a turn-based game on a circular field surrounded by flowers.",
            "timeComplexity": "O(1)",
            "spaceComplexity": "O(1)"
        },
        {
            "id": 3025,
            "title": "Find the Number of Ways to Place People I",
            "route": "/3025",
            "difficulty": "Medium",
            "description": "You are given a 2D array points where points[i] = [xi, yi] represents a point on an X-Y plane.",
            "timeComplexity": "O(n^2)",
            "spaceComplexity": "O(1)"
        },
        {
            "id": 3027,
            "title": "Find the Number of Ways to Place People II",
            "route": "/3027",
            "difficulty": "Hard",
            "description": "You are given a 2D array points where points[i] = [xi, yi] represents a point on an X-Y plane.",
            "timeComplexity": "O(n^2)",
            "spaceComplexity": "O(1)"
        },
        {
            "id": 3047,
            "title": "Find the Largest Area of Square Inside Two Rectangles",
            "route": "/3047",
            "difficulty": "Easy",
            "description": "Find the largest square area that can be formed by the intersection of any two rectangles.",
            "timeComplexity": "O(n^2)",
            "spaceComplexity": "O(1)"
        },
        {
            "id": 3074,
            "title": "Apple Redistribution into Boxes",
            "route": "/3074",
            "difficulty": "Easy",
            "description": "Return the minimum number of boxes needed to redistribute all the apples from the packs into the boxes using greedy strategy.",
            "timeComplexity": "O(m log m + n)",
            "spaceComplexity": "O(1)"
        },
        {
            "id": 3075,
            "title": "Maximize Happiness of Selected Children",
            "route": "/3075",
            "difficulty": "Medium",
            "description": "Maximize the sum of the happiness values of k selected children, accounting for turns and decrements.",
            "timeComplexity": "O(n log n)",
            "spaceComplexity": "O(n)"
        },
        {
            "id": 3100,
            "title": "Water Bottles II",
            "route": "/3100",
            "difficulty": "Medium",
            "description": "You are given two integers numBottles and numExchange.",
            "timeComplexity": "O(log n)",
            "spaceComplexity": "O(1)"
        },
        {
            "id": 3147,
            "title": "Taking Maximum Energy From the Mystic Dungeon",
            "route": "/3147",
            "difficulty": "Medium",
            "description": "In a mystic dungeon, n magicians are standing in a line. Each magician has an attribute that gives you energy.",
            "timeComplexity": "O(n*k)",
            "spaceComplexity": "O(1)"
        },
        {
            "id": 3186,
            "title": "Maximum Total Damage With Spell Casting",
            "route": "/3186",
            "difficulty": "Medium",
            "description": "A magician has various spells.",
            "timeComplexity": "O(n log n)",
            "spaceComplexity": "O(n)"
        },
        {
            "id": 3190,
            "title": "Find Minimum Operations to Make All Elements Divisible by Three",
            "route": "/3190",
            "difficulty": "Easy",
            "description": "You are given an integer array nums. In one operation, you can add or subtract 1 from any element of nums. Return the minimum number of operations to make all elements of nums divisible by 3.",
            "timeComplexity": "O(n)",
            "spaceComplexity": "O(1)"
        },
        {
            "id": 3195,
            "title": "Find the Minimum Area to Cover All Ones I",
            "route": "/3195",
            "difficulty": "Medium",
            "description": "You are given a 2D binary array grid.",
            "timeComplexity": "O(m*n)",
            "spaceComplexity": "O(1)"
        },
        {
            "id": 3197,
            "title": "Minimum Number of Operations to Make Array XOR Equal to K",
            "route": "/3197",
            "difficulty": "Medium",
            "description": "You are given a 0-indexed integer array nums and a positive integer k.",
            "timeComplexity": "O(n)",
            "spaceComplexity": "O(1)"
        },
        {
            "id": 3217,
            "title": "Delete Nodes From Linked List Present in Array",
            "route": "/3217",
            "difficulty": "Medium",
            "description": "You are given an array of integers nums and the head of a linked list. Return the head of the modified linked list after removing all nodes from the linked list that have a value that exists in nums. The order of the nodes should remain the same.",
            "timeComplexity": "O(n + m)",
            "spaceComplexity": "O(m)"
        },
        {
            "id": 3227,
            "title": "Vowels of All Substrings",
            "route": "/3227",
            "difficulty": "Medium",
            "description": "Given a string word, return the sum of the number of vowels ('a', 'e', 'i', 'o', 'u') in every substring of word.",
            "timeComplexity": "O(n)",
            "spaceComplexity": "O(1)"
        },
        {
            "id": 3228,
            "title": "Maximum Number of Operations to Move Ones to the End",
            "route": "/3228",
            "difficulty": "Medium",
            "description": "You are given a binary string s. You can perform the following operation on the string any number of times: Choose any index i from the string where i + 1 < s.length such that s[i]=='1' and s[i + 1]=='0'. Move the character s[i] to the right until it reaches the end of the string or another '1'. Return the maximum number of operations that you can perform.",
            "timeComplexity": "O(n)",
            "spaceComplexity": "O(1)"
        },
        {
            "id": 3234,
            "title": "Count the Number of Substrings With Dominant Ones",
            "route": "/3234",
            "difficulty": "Medium",
            "description": "You are given a binary string s. Return the number of substrings with dominant ones. A string has dominant ones if the number of ones in the string is greater than or equal to the square of the number of zeros in the string.",
            "timeComplexity": "O(n^2)",
            "spaceComplexity": "O(1)"
        },
        {
            "id": 3289,
            "title": "The Two Sneaky Numbers of Digitville",
            "route": "/3289",
            "difficulty": "Easy",
            "description": "In the town of Digitville, there was a list of numbers called nums containing integers from 0 to n - 1. Each number was supposed to appear exactly once in the list, however, two mischievous numbers sneaked in an additional time, making the list longer than usual. As the town detective, your task is to find these two sneaky numbers. Return an array of size two containing the two numbers (in any order), so peace can return to Digitville.",
            "timeComplexity": "O(n log n)",
            "spaceComplexity": "O(1)"
        },
        {
            "id": 3314,
            "title": "Construct the Minimum Bitwise Array I",
            "route": "/3314",
            "difficulty": "Easy",
            "description": "Construct the minimum possible array ans such that the bitwise OR of ans[i] and ans[i] + 1 is equal to nums[i].",
            "timeComplexity": "O(n * log(val))",
            "spaceComplexity": "O(n)"
        },
        {
            "id": 3315,
            "title": "Construct the Minimum Bitwise Array II",
            "route": "/3315",
            "difficulty": "Medium",
            "description": "You are given an array nums consisting of n integers. You need to construct an array ans of length n such that, for each index i, the bitwise OR of ans[i] and ans[i] + 1 is equal to nums[i]. Return...",
            "timeComplexity": "O(n)",
            "spaceComplexity": "O(1)"
        },
        {
            "id": 3318,
            "title": "Find X-Sum of All K-Long Subarrays I",
            "route": "/3318",
            "difficulty": "Medium",
            "description": "You are given an array nums of n integers and two integers k and x. The x-sum of an array is calculated by the following procedure: Count the occurrences of all elements in the array. Keep only the occurrences of the top x most frequent elements. If two elements have the same number of occurrences, the element with the bigger value is considered more frequent. Calculate the sum of the resulting array. Return an integer array answer of length n - k + 1 where answer[i] is the x-sum of the subarray nums[i..i + k - 1].",
            "timeComplexity": "O(n*k)",
            "spaceComplexity": "O(k)"
        },
        {
            "id": 3321,
            "title": "Find X-Sum of All K-Long Subarrays II",
            "route": "/3321",
            "difficulty": "Medium",
            "description": "You are given an array nums of n integers and two integers k and x. The x-sum of an array is calculated by the following procedure: Count the occurrences of all elements in the array. Keep only the occurrences of the top x most frequent elements. If two elements have the same number of occurrences, the element with the bigger value is considered more frequent. Calculate the sum of the resulting array. Return an integer array answer of length n - k + 1 where answer[i] is the x-sum of the subarray nums[i..i + k - 1]. This is the harder version with larger constraints.",
            "timeComplexity": "O(n*k)",
            "spaceComplexity": "O(k)"
        },
        {
            "id": 3346,
            "title": "Determine if a Cell Is Reachable at a Given Time",
            "route": "/3346",
            "difficulty": "Medium",
            "description": "You are given four integers sx, sy, fx, fy, and a non-negative integer t.",
            "timeComplexity": "O(1)",
            "spaceComplexity": "O(1)"
        },
        {
            "id": 3347,
            "title": "Find the Maximum Length of a Good Subsequence I",
            "route": "/3347",
            "difficulty": "Medium",
            "description": "You are given a binary string s and a positive integer k.",
            "timeComplexity": "O(n)",
            "spaceComplexity": "O(1)"
        },
        {
            "id": 3349,
            "title": "Find the Maximum Length of a Good Subsequence II",
            "route": "/3349",
            "difficulty": "Hard",
            "description": "You are given a binary string s and a positive integer k.",
            "timeComplexity": "O(n)",
            "spaceComplexity": "O(1)"
        },
        {
            "id": 3350,
            "title": "Find the Maximum Length of a Good Subsequence III",
            "route": "/3350",
            "difficulty": "Hard",
            "description": "You are given a binary string s and a positive integer k.",
            "timeComplexity": "O(n)",
            "spaceComplexity": "O(1)"
        },
        {
            "id": 3354,
            "title": "Make Array Elements Equal to Zero",
            "route": "/3354",
            "difficulty": "Medium",
            "description": "You are given an integer array nums. Start by selecting a starting position curr such that nums[curr] == 0, and choose a movement direction of either left or right. After that, you repeat the following process: If curr is out of the range [0, n - 1], this process ends. If nums[curr] == 0, move in the current direction by incrementing curr if you are moving right, or decrementing curr if you are moving left. Else if nums[curr] > 0, decrement nums[curr] by 1, and reverse your movement direction (left becomes right and vice versa). Continue the process until you can no longer move. Return the number of possible starting positions and directions that make every element in nums equal to 0.",
            "timeComplexity": "O(n)",
            "spaceComplexity": "O(n)"
        },
        {
            "id": 3370,
            "title": "Smallest Number With All Set Bits",
            "route": "/3370",
            "difficulty": "Easy",
            "description": "You are given a positive integer n. Return the smallest number x greater than or equal to n, such that the binary representation of x contains only set bits (all bits are 1). In other words, return the smallest number that is greater than or equal to n and is of the form 2^k - 1 for some positive integer k.",
            "timeComplexity": "O(1)",
            "spaceComplexity": "O(1)"
        },
        {
            "id": 3381,
            "title": "Maximum Subarray Sum With Length Divisible by K",
            "route": "/3381",
            "difficulty": "Medium",
            "description": "Return the maximum sum of a non-empty subarray of nums, such that the size of the subarray is divisible by k.",
            "timeComplexity": "O(n)",
            "spaceComplexity": "O(k)"
        },
        {
            "id": 3397,
            "title": "Find the Maximum Length of a Good Subsequence IV",
            "route": "/3397",
            "difficulty": "Hard",
            "description": "You are given a binary string s and a positive integer k.",
            "timeComplexity": "O(n)",
            "spaceComplexity": "O(1)"
        },
        {
            "id": 3408,
            "title": "Find the Maximum Length of a Good Subsequence V",
            "route": "/3408",
            "difficulty": "Hard",
            "description": "You are given a binary string s and a positive integer k.",
            "timeComplexity": "O(n)",
            "spaceComplexity": "O(1)"
        },
        {
            "id": 3432,
            "title": "Count Partitions with Even Sum Difference",
            "route": "/3432",
            "difficulty": "Easy",
            "description": "Return the number of ways to partition nums such that the absolute difference between the sum of the first i + 1 elements and the sum of the remaining elements is even.",
            "timeComplexity": "O(n)",
            "spaceComplexity": "O(1)"
        },
        {
            "id": 3433,
            "title": "Count Mentions Per User",
            "route": "/3433",
            "difficulty": "Medium",
            "description": "Return an array where the ith element is the total number of times user i was mentioned across all messages.",
            "timeComplexity": "O(N log N)",
            "spaceComplexity": "O(N)"
        },
        {
            "id": 3446,
            "title": "Find the Maximum Length of a Good Subsequence VI",
            "route": "/3446",
            "difficulty": "Hard",
            "description": "You are given a binary string s and a positive integer k.",
            "timeComplexity": "O(n)",
            "spaceComplexity": "O(1)"
        },
        {
            "id": 3453,
            "title": "Separate Squares I",
            "route": "/3453",
            "difficulty": "Medium",
            "description": "Find the y-coordinate of a horizontal line that divides the total area of all non-overlapping squares into two equal halves.",
            "timeComplexity": "O(n * log(precision))",
            "spaceComplexity": "O(n)"
        },
        {
            "id": 3454,
            "title": "Separate Squares II",
            "route": "/3454",
            "difficulty": "Hard",
            "description": "Find the y-coordinate of a horizontal line that divides the total union area of overlapping squares into two equal halves.",
            "timeComplexity": "O(n log n)",
            "spaceComplexity": "O(n)"
        },
        {
            "id": 3459,
            "title": "Find the Maximum Length of a Good Subsequence VII",
            "route": "/3459",
            "difficulty": "Hard",
            "description": "You are given a binary string s and a positive integer k.",
            "timeComplexity": "O(n)",
            "spaceComplexity": "O(1)"
        },
        {
            "id": 3461,
            "title": "Find the Maximum Length of a Good Subsequence VIII",
            "route": "/3461",
            "difficulty": "Hard",
            "description": "You are given a binary string s and a positive integer k.",
            "timeComplexity": "O(n)",
            "spaceComplexity": "O(1)"
        },
        {
            "id": 3484,
            "title": "Find the Maximum Length of a Good Subsequence IX",
            "route": "/3484",
            "difficulty": "Hard",
            "description": "You are given a binary string s and a positive integer k.",
            "timeComplexity": "O(n)",
            "spaceComplexity": "O(1)"
        },
        {
            "id": 3494,
            "title": "Find the Maximum Length of a Good Subsequence X",
            "route": "/3494",
            "difficulty": "Hard",
            "description": "You are given a binary string s and a positive integer k.",
            "timeComplexity": "O(n)",
            "spaceComplexity": "O(1)"
        },
        {
            "id": 3495,
            "title": "Find the Maximum Length of a Good Subsequence XI",
            "route": "/3495",
            "difficulty": "Hard",
            "description": "You are given a binary string s and a positive integer k.",
            "timeComplexity": "O(n)",
            "spaceComplexity": "O(1)"
        },
        {
            "id": 3507,
            "title": "Minimum Pair Removal to Sort Array I",
            "route": "/3507",
            "difficulty": "Medium",
            "description": "You are given an array of integers nums. In one operation, you can select any two adjacent elements, remove them, and replace them with their sum. Return the minimum number of operations required t...",
            "timeComplexity": "O(n)",
            "spaceComplexity": "O(1)"
        },
        {
            "id": 3508,
            "title": "Find the Maximum Length of a Good Subsequence XII",
            "route": "/3508",
            "difficulty": "Hard",
            "description": "You are given a binary string s and a positive integer k.",
            "timeComplexity": "O(n)",
            "spaceComplexity": "O(1)"
        },
        {
            "id": 3510,
            "title": "Minimum Pair Removal to Sort Array II",
            "route": "/3510",
            "difficulty": "Medium",
            "description": "You are given an array of integers nums. In one operation, you can select any two adjacent elements, remove them, and replace them with their sum. Return the minimum number of operations required t...",
            "timeComplexity": "O(n)",
            "spaceComplexity": "O(1)"
        },
        {
            "id": 3512,
            "title": "Minimum Operations to Make Array Sum Divisible by K",
            "route": "/3512",
            "difficulty": "Easy",
            "description": "In one operation, you can decrease any element of nums by 1. Return the minimum number of operations required to make the sum of all elements in nums divisible by k.",
            "timeComplexity": "O(n)",
            "spaceComplexity": "O(1)"
        },
        {
            "id": 3516,
            "title": "Find the Maximum Length of a Good Subsequence XIII",
            "route": "/3516",
            "difficulty": "Hard",
            "description": "You are given a binary string s and a positive integer k.",
            "timeComplexity": "O(n)",
            "spaceComplexity": "O(1)"
        },
        {
            "id": 3531,
            "title": "Count Covered Buildings",
            "route": "/3531",
            "difficulty": "Medium",
            "description": "Return the number of covered buildings on a grid.",
            "timeComplexity": "O(N log N)",
            "spaceComplexity": "O(N)"
        },
        {
            "id": 3539,
            "title": "Find the Maximum Length of a Good Subsequence XIV",
            "route": "/3539",
            "difficulty": "Hard",
            "description": "You are given a binary string s and a positive integer k.",
            "timeComplexity": "O(n)",
            "spaceComplexity": "O(1)"
        },
        {
            "id": 3541,
            "title": "Find the Maximum Length of a Good Subsequence XV",
            "route": "/3541",
            "difficulty": "Hard",
            "description": "You are given a binary string s and a positive integer k.",
            "timeComplexity": "O(n)",
            "spaceComplexity": "O(1)"
        },
        {
            "id": 3542,
            "title": "Minimum Operations to Convert All Elements to Zero",
            "route": "/3542",
            "difficulty": "Medium",
            "description": "You are given an integer array nums. In one operation, you can select a subarray and decrement all its elements by 1. Return the minimum number of operations needed to make all elements in nums equal to 0. You need to efficiently track when segments of the array decrease and count the total operations required.",
            "timeComplexity": "O(n)",
            "spaceComplexity": "O(n)"
        },
        {
            "id": 3562,
            "title": "Maximum Profit from Trading Stocks with Discounts",
            "route": "/3562",
            "difficulty": "Hard",
            "description": "Return the maximum profit you can achieve by trading stocks with a discount.",
            "timeComplexity": "O(N * Budget^2)",
            "spaceComplexity": "O(N * Budget)"
        },
        {
            "id": 3573,
            "title": "Best Time to Buy and Sell Stock V",
            "route": "/3573",
            "difficulty": "Medium",
            "description": "Return the maximum profit you can achieve with at most K transactions.",
            "timeComplexity": "O(N * K)",
            "spaceComplexity": "O(K)"
        },
        {
            "id": 3577,
            "title": "Count the Number of Computer Unlocking Permutations",
            "route": "/3577",
            "difficulty": "Medium",
            "description": "Return the number of valid unlocking permutations modulo 10^9 + 7.",
            "timeComplexity": "O(N)",
            "spaceComplexity": "O(1)"
        },
        {
            "id": 3578,
            "title": "Count Partitions With Max-Min Difference at Most K",
            "route": "/3578",
            "difficulty": "Medium",
            "description": "Return the number of valid ways to partition nums such that max-min difference is at most k.",
            "timeComplexity": "O(N log N)",
            "spaceComplexity": "O(N)"
        },
        {
            "id": 3583,
            "title": "Count Special Triplets",
            "route": "/3583",
            "difficulty": "Medium",
            "description": "Return the number of special triplets modulo 10^9 + 7.",
            "timeComplexity": "O(n)",
            "spaceComplexity": "O(n)"
        },
        {
            "id": 3606,
            "title": "Coupon Code Validator",
            "route": "/3606",
            "difficulty": "Medium",
            "description": "Return a list of valid coupon codes sorted by priority.",
            "timeComplexity": "O(N log N)",
            "spaceComplexity": "O(N)"
        },
        {
            "id": 3607,
            "title": "Power Grid Maintenance",
            "route": "/3607",
            "difficulty": "Hard",
            "description": "You are managing a power grid with n power stations numbered from 1 to n. Some stations are connected by power lines given in the connections array where connections[i] = [a, b] means stations a and b are connected. You need to process queries of two types: Type 1 [1, x] - maintenance check: if station x is online, return x; otherwise return the smallest numbered online station connected to x, or -1 if none exist. Type 2 [2, x] - turn off station x for maintenance. Return an array containing answers to all type 1 queries.",
            "timeComplexity": "O(n + m + q)",
            "spaceComplexity": "O(n + m)"
        },
        {
            "id": 3623,
            "title": "Count Number of Trapezoids I",
            "route": "/3623",
            "difficulty": "Medium",
            "description": "Return the number of different trapezoids that can be formed.",
            "timeComplexity": "O(n)",
            "spaceComplexity": "O(n)"
        },
        {
            "id": 3625,
            "title": "Count Number of Trapezoids II",
            "route": "/3625",
            "difficulty": "Hard",
            "description": "Return the number of different trapezoids that can be formed with general slopes.",
            "timeComplexity": "O(n^2)",
            "spaceComplexity": "O(n^2)"
        },
        {
            "id": 3650,
            "title": "Minimum Cost Path with Edge Reversals",
            "route": "/3650",
            "difficulty": "Medium",
            "description": "You are given an integer n representing the number of nodes in a directed graph, and a 2D integer array edges where edges[i] = [u, v, cost] denotes a directed edge from node u to node v with a cost...",
            "timeComplexity": "O(n)",
            "spaceComplexity": "O(1)"
        },
        {
            "id": 3651,
            "title": "Minimum Cost Path with Teleportations",
            "route": "/3651",
            "difficulty": "Medium",
            "description": "You are given an m x n integer matrix grid and an integer k. You start at the top-left cell (0, 0) and want to reach the bottom-right cell (m-1, n-1). You can move right or down, and each move to a...",
            "timeComplexity": "O(n)",
            "spaceComplexity": "O(1)"
        },
        {
            "id": 3652,
            "title": "Best Time to Buy and Sell Stock using Strategy",
            "route": "/3652",
            "difficulty": "Hard",
            "description": "Return the maximum profit you can achieve with a trading strategy and overrides.",
            "timeComplexity": "O(n)",
            "spaceComplexity": "O(n)"
        },
        {
            "id": 9999,
            "title": "Workflow Test",
            "route": "/9999",
            "difficulty": "Medium",
            "description": "This is a test problem to verify the automated GitHub Actions synchronization workflow (whitespace cleaning verified).",
            "timeComplexity": "O(n)",
            "spaceComplexity": "O(1)"
        },
        {
            "id": 99999,
            "title": "Workflow Test",
            "route": "/99999",
            "difficulty": "Medium",
            "description": "This is a test problem to verify the automated GitHub Actions synchronization\n                workflow (permissions fix verified).",
            "timeComplexity": "O(n)",
            "spaceComplexity": "O(1)"
        }
    ],
    "totalCount": 152,
    "lastUpdated": "2026-01-30"
}